tests/__init__.py
tests/test_project_generation.py
cookiecutter_fastapi-0.1.3.dist-info/LICENSE
cookiecutter_fastapi-0.1.3.dist-info/WHEEL
cookiecutter_fastapi-0.1.3.dist-info/METADATA
cookiecutter_fastapi-0.1.3.dist-info/RECORD
