Metadata-Version: 2.1
Name: cookiecutter-fastapi
Version: 0.1.3
Summary: Cookiecutter for fastapi projects
Home-page: https://cookiecutter-fastapi.readthedocs.io/en/latest/
License: MIT
Keywords: fastapi,python,cookiecutter,project template,tortoise-orm,beanie,SQLModel
Author: Tobi-De
Author-email: tobidegnon@proton.me
Requires-Python: >=3.9,<4.0
Classifier: Development Status :: 5 - Production/Stable
Classifier: Environment :: Console
Classifier: Framework :: FastAPI
Classifier: Intended Audience :: Developers
Classifier: License :: OSI Approved :: BSD License
Classifier: License :: OSI Approved :: MIT License
Classifier: Natural Language :: English
Classifier: Programming Language :: Python
Classifier: Programming Language :: Python :: 3
Classifier: Programming Language :: Python :: 3.9
Classifier: Programming Language :: Python :: 3.10
Classifier: Programming Language :: Python :: 3.11
Classifier: Programming Language :: Python :: 3
Classifier: Programming Language :: Python :: 3.10
Classifier: Programming Language :: Python :: 3.8
Classifier: Programming Language :: Python :: 3.9
Classifier: Programming Language :: Python :: Implementation :: CPython
Classifier: Topic :: Software Development
Requires-Dist: cookiecutter (>=2.1.1,<3.0.0)
Requires-Dist: furo (>=2022.12.7,<2023.0.0)
Requires-Dist: pytest (>=7.2.0,<8.0.0)
Requires-Dist: pytest-cookies (>=0.6.1,<0.7.0)
Project-URL: Documentation, https://cookiecutter-fastapi.readthedocs.io/en/latest/
Project-URL: Repository, https://github.com/Tobi-De/cookiecutter-fastapi
